odoo/addons/task_requirements_mgmt/README.rst
odoo/addons/task_requirements_mgmt/__init__.py
odoo/addons/task_requirements_mgmt/__manifest__.py
odoo/addons/task_requirements_mgmt/i18n/es.po
odoo/addons/task_requirements_mgmt/models/__init__.py
odoo/addons/task_requirements_mgmt/models/project_task.py
odoo/addons/task_requirements_mgmt/models/task_requirement.py
odoo/addons/task_requirements_mgmt/readme/CONFIGURE.rst
odoo/addons/task_requirements_mgmt/readme/CONTRIBUTORS.rst
odoo/addons/task_requirements_mgmt/readme/DESCRIPTION.rst
odoo/addons/task_requirements_mgmt/readme/USAGE.rst
odoo/addons/task_requirements_mgmt/security/ir.model.access.csv
odoo/addons/task_requirements_mgmt/static/description/icon.png
odoo/addons/task_requirements_mgmt/static/description/index.html
odoo/addons/task_requirements_mgmt/tests/__init__.py
odoo/addons/task_requirements_mgmt/tests/test_task_requirements_mgmt.py
odoo/addons/task_requirements_mgmt/views/project_views.xml
odoo_addon_task_requirements_mgmt-16.0.1.0.0.1.dist-info/METADATA
odoo_addon_task_requirements_mgmt-16.0.1.0.0.1.dist-info/WHEEL
odoo_addon_task_requirements_mgmt-16.0.1.0.0.1.dist-info/top_level.txt
odoo_addon_task_requirements_mgmt-16.0.1.0.0.1.dist-info/RECORD
